pyjce/__init__.py
pyjce/bytebuffer.py
pyjce/exception.py
pyjce/stream.py
pyjce/struct.py
PyJce-0.0.1.dist-info/LICENSE
PyJce-0.0.1.dist-info/METADATA
PyJce-0.0.1.dist-info/WHEEL
PyJce-0.0.1.dist-info/top_level.txt
PyJce-0.0.1.dist-info/RECORD
